_dummy.cp38-win_amd64.pyd
include/__init__.py
lib/__init__.py
clangTooling-0.0.3.dist-info/METADATA
clangTooling-0.0.3.dist-info/WHEEL
clangTooling-0.0.3.dist-info/top_level.txt
clangTooling-0.0.3.dist-info/RECORD
