Metadata-Version: 2.1
Name: clangTooling
Version: 0.0.3
Summary: clangTooling static libraries
Home-page: https://github.com/mckib2/clangTooling
Author: Nicholas McKibben
Author-email: nicholas.bgp@gmail.com
License: MIT
Keywords: clang
Platform: UNKNOWN
Requires-Python: >=3.6
